tycho/__init__.py
tycho/de.py
tycho/decode.py
tycho/elements.py
tycho/length.py
tycho/ser.py
tycho/string.py
tycho/values.py
tycho_py-0.1.5.dist-info/LICENSE
tycho_py-0.1.5.dist-info/METADATA
tycho_py-0.1.5.dist-info/WHEEL
tycho_py-0.1.5.dist-info/top_level.txt
tycho_py-0.1.5.dist-info/RECORD
