Metadata-Version: 2.1
Name: tycho-py
Version: 0.1.5
Summary: A python implementation of the Tycho binary format
Home-page: https://github.com/samhdev/tycho-py
Author: SamHDev
Author-email: sam.fucked.up@samh.dev
License: UNKNOWN
Platform: UNKNOWN
Classifier: Programming Language :: Python :: 3
Classifier: License :: OSI Approved :: MIT License
Classifier: Operating System :: OS Independent
Requires-Python: >=3.6
